kmeans_smote.py
kmeans_smote-0.1.2.dist-info/LICENSE
kmeans_smote-0.1.2.dist-info/METADATA
kmeans_smote-0.1.2.dist-info/WHEEL
kmeans_smote-0.1.2.dist-info/top_level.txt
kmeans_smote-0.1.2.dist-info/RECORD
