Metadata-Version: 2.1
Name: kmeans-smote
Version: 0.1.2
Summary: Oversampling for imbalanced learning based on k-means and SMOTE
Home-page: https://github.com/felix-last/kmeans_smote
Author: Felix Last
Author-email: mail@felixlast.de
License: MIT
Keywords: Class-imbalanced Learning,Oversampling,Classification,Clustering,Supervised Learning
Platform: UNKNOWN
Classifier: License :: OSI Approved :: MIT License
Classifier: Topic :: Scientific/Engineering
Classifier: Topic :: Scientific/Engineering :: Information Analysis
Classifier: Intended Audience :: Science/Research
Classifier: Intended Audience :: Developers
Classifier: Programming Language :: Python
Classifier: Programming Language :: Python :: 3.6
Classifier: Operating System :: Microsoft :: Windows
Classifier: Operating System :: POSIX
Classifier: Operating System :: Unix
Classifier: Operating System :: MacOS
Requires-Dist: imbalanced-learn (<0.5,>=0.4.0)
Requires-Dist: scikit-learn (<0.21,>=0.19.0)
Requires-Dist: numpy (<1.16,>=1.13)
Provides-Extra: test
Requires-Dist: pytest (<4.3,>=4.2.1) ; extra == 'test'
Requires-Dist: pytest-cov (<2.7,>=2.6.1) ; extra == 'test'
Requires-Dist: codecov (<2.1,>=2.0.15) ; extra == 'test'
